scrapy_scrapingfish/__init__.py
scrapy_scrapingfish/middleware.py
scrapy_scrapingfish-0.0.2.dist-info/licenses/LICENSE
scrapy_scrapingfish-0.0.2.dist-info/METADATA
scrapy_scrapingfish-0.0.2.dist-info/WHEEL
scrapy_scrapingfish-0.0.2.dist-info/top_level.txt
scrapy_scrapingfish-0.0.2.dist-info/RECORD
