Metadata-Version: 2.4
Name: scrapy-scrapingfish
Version: 0.0.2
Summary: A Scrapy downloader middleware for ScrapingFish
Author-email: Łukasz Żarnowiecki <lukasz.zarnowiecki@narf.ai>
License-Expression: MIT
Classifier: Programming Language :: Python
Classifier: Programming Language :: Python :: 3
Classifier: Programming Language :: Python :: 3.9
Classifier: Programming Language :: Python :: 3.10
Classifier: Programming Language :: Python :: 3.11
Classifier: Programming Language :: Python :: 3.12
Classifier: Programming Language :: Python :: 3.13
Classifier: Programming Language :: Python :: 3.13
Requires-Python: >=3.9
License-File: LICENSE
Requires-Dist: aiohttp>=3.12.12
Requires-Dist: scrapy>=2.13.0
Dynamic: license-file
